README.md
setup.py
pyfb/__init__.py
pyfb/auth.py
pyfb/client.py
pyfb/pyfb.py
pyfb/utils.py
pyfb.egg-info/PKG-INFO
pyfb.egg-info/SOURCES.txt
pyfb.egg-info/dependency_links.txt
pyfb.egg-info/requires.txt
pyfb.egg-info/top_level.txt