Metadata-Version: 1.0
Name: pyfb
Version: 0.5.0
Summary: A Python Interface to the Facebook Graph API
Home-page: http://code.google.com/p/pyfb/
Author: Juan Manuel Garcia
Author-email: jmg.utn@gmail.com
License: GPL v3
Keywords: Facebook Graph API Wrapper Python
Platform: UNKNOWN
